setup.py
easy_linear_algebra/__init__.py
easy_linear_algebra.egg-info/PKG-INFO
easy_linear_algebra.egg-info/SOURCES.txt
easy_linear_algebra.egg-info/dependency_links.txt
easy_linear_algebra.egg-info/top_level.txt