Metadata-Version: 2.1
Name: easy-linear-algebra
Version: 0.0.1
Summary: A module that helps you to calculate easy linear algebra calculations.
Home-page: https://github.com/
Author: Gordon_Shi
Author-email: gordon2028261@concordiashanghai.org
Classifier: Programming Language :: Python :: 3
Classifier: License :: OSI Approved :: MIT License
Classifier: Operating System :: OS Independent
